moneytalks/__init__.py
moneytalks/converter.py
tests/__init__.py
tests/test_converter.py
moneytalks-0.1.dist-info/LICENSE
moneytalks-0.1.dist-info/METADATA
moneytalks-0.1.dist-info/WHEEL
moneytalks-0.1.dist-info/top_level.txt
moneytalks-0.1.dist-info/RECORD
