Metadata-Version: 2.1
Name: moneytalks
Version: 0.1
Summary: Convert numbers to ru currency strings
Home-page: https://github.com/SupreLTD/moneytalks
Author: Ivan Dovbnya
Author-email: supreltd@gmail.com
License: GNU
Classifier: Programming Language :: Python :: 3
Classifier: License :: OSI Approved :: MIT License
Classifier: Operating System :: OS Independent
Requires-Python: >=3.6
License-File: LICENSE
